{
  "week_number": 50,
  "week_start": "2025-12-08",
  "week_end": "2025-12-14",
  "country": "india",
  "categories": [
    {
      "category_id": "bollywood-hindi",
      "category_name": "Bollywood (Hindi)",
      "movies": [
        {
          "title": "Mahasenha",
          "release_date": "2025-12-12",
          "genre": "Action/Drama",
          "language": "Hindi",
          "additional_languages": [],
          "cast": [
            "Vimal",
            "Srushti"
          ],
          "director": "TBA",
          "production": "TBA",
          "description": "Listed as a December theatrical release; details (director/production) were not publicly confirmed in primary listings I searched and remain TBA."
        },
        {
          "title": "Mere Raho",
          "release_date": "2025-12-12",
          "genre": "Drama",
          "language": "Hindi",
          "additional_languages": [],
          "cast": [
            "TBA"
          ],
          "director": "TBA",
          "production": "TBA",
          "description": "Appears on multiple upcoming Hindi release listings with a confirmed theatrical date of 2025-12-12 but public sources I found do not list full crew/cast details."
        },
        {
          "title": "Kis Kisko Pyaar Karoon 2",
          "release_date": "2025-12-12",
          "genre": "Comedy",
          "language": "Hindi",
          "additional_languages": [],
          "cast": [
            "Kapil Sharma",
            "Manjot Singh"
          ],
          "director": "TBA",
          "production": "TBA",
          "description": "Listed for theatrical release on 2025-12-12 in Bollywood release roundups; specific production credits in public listings searched are incomplete."
        }
      ]
    },
    {
      "category_id": "regional-telugu",
      "category_name": "Regional (Telugu)",
      "movies": [
        {
          "title": "Mahasenha",
          "release_date": "2025-12-12",
          "genre": "Action/Drama",
          "language": "Telugu",
          "additional_languages": [],
          "cast": [
            "Vimal",
            "Srushti"
          ],
          "director": "TBA",
          "production": "TBA",
          "description": "Appears in Telugu upcoming lists with a theatrical date of 2025-12-12 in aggregated listings; production and director details not confirmed in sources found."
        },
        {
          "title": "Rachel",
          "release_date": "2025-12-12",
          "genre": "Drama",
          "language": "Telugu",
          "additional_languages": [],
          "cast": [
            "TBA"
          ],
          "director": "TBA",
          "production": "TBA",
          "description": "Listed by Telugu upcoming movie aggregators for 2025-12-12; full credits not available in the sources I reviewed."
        }
      ]
    },
    {
      "category_id": "regional-tamil",
      "category_name": "Regional (Tamil)",
      "movies": [
        {
          "title": "Mysaa",
          "release_date": "2025-12-01",
          "genre": "Drama",
          "language": "Tamil",
          "additional_languages": [],
          "cast": [
            "Rashmika Mandanna"
          ],
          "director": "TBA",
          "production": "TBA",
          "description": "Listed in month-based Bollywood/Tamil roundups as releasing 2025-12-01; public listings I accessed show the date but not all production details."
        }
      ]
    },
    {
      "category_id": "regional-other",
      "category_name": "Regional (Other)",
      "movies": [
        {
          "title": "Champion",
          "release_date": "2025-12-25",
          "genre": "Action/Drama",
          "language": "Telugu",
          "additional_languages": [],
          "cast": [
            "Roshann Meka",
            "Anaswara Rajan",
            "Kruthi Kanj Singh Rathod"
          ],
          "director": "Pradeep Advaitham",
          "production": "Swapna Cinema / Anandi Art Creations / Concept / Zee Studios",
          "description": "Confirmed Telugu theatrical release for 2025-12-25 in major Telugu release trackers and news roundups; listed here under Regional (Other) to include non-Hindi regional releases outside Tamil/Kannada/Malayalam categories."
        },
        {
          "title": "Vrusshabha",
          "release_date": "2025-12-25",
          "genre": "Drama",
          "language": "Kannada",
          "additional_languages": [
            "Telugu"
          ],
          "cast": [
            "Mohanlal",
            "Samarjit Lankesh",
            "Siddique"
          ],
          "director": "Nanda Kishore",
          "production": "TBA",
          "description": "Listed as a December theatrical release (25 Dec 2025) in regional upcoming movie lists; sources indicate a multi-language presence (Kannada/Telugu) though some production details remain unconfirmed in the public trackers searched."
        },
        {
          "title": "Eesha",
          "release_date": "2025-12-25",
          "genre": "Drama",
          "language": "Telugu",
          "additional_languages": [],
          "cast": [
            "Thrigun",
            "Hebah Patel"
          ],
          "director": "Srinivas Manne",
          "production": "HVR Productions",
          "description": "Listed on Telugu film lists for theatrical release on 2025-12-25 with credited director and production in the Telugu film listings I reviewed."
        }
      ]
    }
  ]
}