{
  "week_number": "2025-51",
  "week_start": "2025-12-15",
  "week_end": "2025-12-21",
  "country": "us",
  "categories": [
    {
      "id": "wide-release",
      "name": "Wide Release",
      "movies": [
        {
          "title": "Avatar: Fire and Ash",
          "release_date": "2025-12-19",
          "genre": "Action, Adventure, Fantasy",
          "rating": "PG-13",
          "studio": "20th Century Studios",
          "cast": [
            "Sam Worthington",
            "Zoe Saldaña",
            "Sigourney Weaver",
            "Stephen Lang"
          ],
          "director": "James Cameron",
          "theater_count": "4,000+ theaters",
          "description": "The third installment in the Avatar franchise follows Jake Sully and Neytiri as they confront new threats on Pandora in James Cameron's epic sci-fi saga."
        },
        {
          "title": "The SpongeBob Movie: Search for SquarePants",
          "release_date": "2025-12-19",
          "genre": "Animation, Adventure, Comedy",
          "rating": "PG",
          "studio": "Paramount Pictures",
          "cast": [
            "Tom Kenny",
            "Rodger Bumpass",
            "Bill Fagerbakke"
          ],
          "director": "Derek Drymon",
          "theater_count": "3,800+ theaters",
          "description": "SpongeBob and friends embark on a heroic journey through Bikini Bottom and the underworld to save Gary and break a curse in this animated family adventure."
        },
        {
          "title": "The Housemaid",
          "release_date": "2025-12-19",
          "genre": "Thriller",
          "rating": "R",
          "studio": "Warner Bros.",
          "cast": [
            "Sydney Sweeney",
            "Amanda Seyfried",
            "Brandon Sklenar"
          ],
          "director": "Paul Feig",
          "theater_count": "2,500+ theaters",
          "description": "A tense psychological thriller adaptation where a housemaid uncovers dark secrets in a wealthy family's home, starring Sydney Sweeney and Amanda Seyfried."
        }
      ]
    },
    {
      "id": "limited-release",
      "name": "Limited Release",
      "movies": [
        {
          "title": "David",
          "release_date": "2025-12-19",
          "genre": "Drama",
          "rating": "PG",
          "studio": "Angel Studios",
          "cast": [
            "Jim Caviezel"
          ],
          "director": "Nick Hahn",
          "theater_count": "500-1,000 theaters",
          "description": "A shepherd faces divine challenges and follows a heavenly light in this faith-based Christmas drama celebrating the holiday season."
        },
        {
          "title": "AMC Screen Unseen: December 15",
          "release_date": "2025-12-15",
          "genre": "Unknown",
          "rating": "NR",
          "studio": "AMC Theatres",
          "cast": [],
          "director": "",
          "theater_count": "50-100 theaters",
          "description": "AMC's mystery screening event where audiences discover the film only after purchase, a platform-style limited release."
        },
        {
          "title": "The Royal Ballet: The Nutcracker",
          "release_date": "2025-12-21",
          "genre": "Performance",
          "rating": "NR",
          "studio": "Royal Ballet",
          "cast": [],
          "director": "",
          "theater_count": "100-300 theaters",
          "description": "Live recording of the classic Royal Ballet production of The Nutcracker, a holiday tradition screened in select theaters nationwide."
        }
      ]
    }
  ]
}